{

  "TransactionHistory": [

    {

        "transactionAmount": 4456.32,

        "paymentType": "Salary",

        "transactionUser": "Abc",

        "transactionPlace": "Address 1",

        "transactionCurrency": "Kc",

        "transactionDate": 1345345335345

    },

    {

        "transactionAmount": 5234.56,

        "paymentType": "Fee",

        "transactionUser": "Abc",

        "transactionPlace": "Address 2",

        "transactionCurrency": "Kc",

        "transactionDate": 1345345335345

    },

    {

        "transactionAmount": 2456.65,

        "paymentType": "Interest",

        "transactionUser": "Abc",

        "transactionPlace": "Address 3",

        "transactionCurrency": "Kc",

        "transactionDate": 1345345335345

    },

    {

        "transactionAmount": 5643.76,

        "paymentType": "Income",

        "transactionUser": "Abc",

        "transactionPlace": "Address 4",

        "transactionCurrency": "Kc",

        "transactionDate": 1345345335345

    },

    {

        "transactionAmount": 9234.45,

        "paymentType": "PFM Category 1",

        "transactionUser": "Abc",

        "transactionPlace": "Address 5",

        "transactionCurrency": "Kc",

        "transactionDate": 1345345335345

    },

    {

        "transactionAmount": 3826.90,

        "paymentType": "Tax",

        "transactionUser": "Abc",

        "transactionPlace": "Address 6",

        "transactionCurrency": "Kc",

        "transactionDate": 1345345335345

    }

  ]

}
